{
	"data":[
		{
			"list1":"家用电器",
			"list2top":[
				{
					"topname":"家电馆"
				},
				{
					"topname":"家电专卖店"
				},
				{
					"topname":"家电服务"
				},
				{
					"topname":"企业采购"
				},
				{
					"topname":"商用电器"
				}
			],
			"list2left":[
				{
					"leftname":"电视",
					"list3":[
						{
							"list3name":"超薄电视"
						},
						{
							"list3name":"全面屏电视"
						},
						{
							"list3name":"智能电视"
						},
						{
							"list3name":"OLED电视"
						},
						{
							"list3name":"曲面电视"
						},
						{
							"list3name":"4K超清电视"
						},
						{
							"list3name":"55英寸"
						},
						{
							"list3name":"65英寸"
						},
						{
							"list3name":"电视配件"
						}
					]
				},
				{    
    
					"leftname":"空调",
					"list3":[
						{
							"list3name":"空调挂机"
						},
						{
							"list3name":"空调柜机"
						},
						{
							"list3name":"精选推荐"
						},
						{
							"list3name":"中央空调"
						},
						{
							"list3name":"移动空调"
						},
						{
							"list3name":"省电空调"
						},
						{
							"list3name":"变频空调"
						},
						{
							"list3name":"以旧换新"
						}
					]
				},
				{    

					"leftname":"洗衣机",
					"list3":[
						{
							"list3name":"滚筒洗衣机"
						},
						{
							"list3name":"洗烘一体机"
						},
						{
							"list3name":"波轮洗衣机"
						},
						{
							"list3name":"迷你洗衣机"
						},
						{
							"list3name":"烘干机"
						},
						{
							"list3name":"洗衣机配件"
						}
					]
				},
				{    
        
					"leftname":"冰箱",
					"list3":[
						{
							"list3name":"多门"
						},
						{
							"list3name":"对开门"
						},
						{
							"list3name":"三门"
						},
						{
							"list3name":"双门"
						},
						{
							"list3name":"冷柜/冰吧"
						},
						{
							"list3name":"酒柜"
						},
						{
							"list3name":"冰箱配件"
						}
					]
				},
				{    
        
					"leftname":"厨卫大电",
					"list3":[
						{
							"list3name":"油烟机"
						},
						{
							"list3name":"燃气灶"
						},
						{
							"list3name":"烟灶套装"
						},
						{
							"list3name":"中集成灶"
						},
						{
							"list3name":"消毒柜"
						},
						{
							"list3name":"洗碗机"
						},
						{
							"list3name":"电热水器"
						},
						{
							"list3name":"燃气热水器"
						},
						{
							"list3name":"空气能热水器"
						},
						{
							"list3name":"太阳能热水器"
						},
						{
							"list3name":"嵌入式厨电"
						},
						{
							"list3name":"烟机灶具配件"
						}
					]
				},
				{    
        
					"leftname":"厨房小电",
					"list3":[
						{
							"list3name":"破壁机"
						},
						{
							"list3name":"电烤箱"
						},
						{
							"list3name":"电饭煲"
						},
						{
							"list3name":"电压力锅"
						},
						{
							"list3name":"电炖锅"
						},
						{
							"list3name":"豆浆机"
						},
						{
							"list3name":"料理机"
						},
						{
							"list3name":"咖啡机"
						},
						{
							"list3name":"电饼铛"
						},
						{
							"list3name":"榨汁机/原汁机"
						},
						{
							"list3name":"电水壶/热水瓶"
						},
						{
							"list3name":"微波炉"
						},
						{
							"list3name":"多用途锅"
						},
						{
							"list3name":"养生壶"
						},
						{
							"list3name":"电磁炉"
						},
						{
							"list3name":"面包机"
						},
						{
							"list3name":"空气炸锅"
						},
						{
							"list3name":"面条机"
						},
						{
							"list3name":"电陶炉"
						},
						{
							"list3name":"煮蛋器"
						},
						{
							"list3name":"电烧烤炉"
						}
					]
				},
				{    
        
					"leftname":"生活电器",
					"list3":[
						{
							"list3name":"电风扇"
						},
						{
							"list3name":"冷风扇"
						},
						{
							"list3name":"空气净化器"
						},
						{
							"list3name":"吸尘器"
						},
						{
							"list3name":"除螨仪"
						},
						{
							"list3name":"扫地机器人"
						},
						{
							"list3name":"除湿机"
						},
						{
							"list3name":"干衣机"
						},{
							"list3name":"加湿器"
						},
						{
							"list3name":"蒸汽拖把/拖地机"
						},
						{
							"list3name":"挂烫机/熨斗"
						},
						{
							"list3name":"电话机"
						},
						{
							"list3name":"饮水机"
						},
						{
							"list3name":"净水器"
						},
						{
							"list3name":"取暖电器"
						},
						{
							"list3name":"毛球修剪器"
						},
						{
							"list3name":"生活电器配件"
						}
					]
				},
				{    
        
					"leftname":"个户健康",
					"list3":[
						{
							"list3name":"剃须刀"
						},
						{
							"list3name":"电动牙刷"
						},
						{
							"list3name":"电吹风"
						},
						{
							"list3name":"美容器"
						},
						{
							"list3name":"洁面仪"
						},
						{
							"list3name":"按摩器"
						},
						{
							"list3name":"健康秤"
						},
						{
							"list3name":"卷/直发器"
						},
						{
							"list3name":"剃/脱毛器"
						},
						{
							"list3name":"理发器"
						},
						{
							"list3name":"足浴盆"
						},
						{
							"list3name":"足疗机"
						},
						{
							"list3name":"按摩椅"
						}
					]
				},
				{    
    
					"leftname":"视听影音",
					"list3":[
						{
							"list3name":"家庭影院"
						},
						{
							"list3name":"KTV音响"
						},
						{
							"list3name":"迷你音响"
						},
						{
							"list3name":"DVD"
						},
						{
							"list3name":"功放"
						},
						{
							"list3name":"回音壁"
						},
						{
							"list3name":"麦克风"
						}
					]
				}
			]
		},
		{
			"list1":"手机/运营商/数码",
			"list2top":[

				{
					"topname":"玩3C"
				},
				{
					"topname":"手机频道"
				},
				{
					"topname":"网上营业厅"
				},
				{
					"topname":"配件选购中心"
				},
				{
					"topname":"智能数码"
				},
				{
					"topname":"影像Club"
				}
			],
			"list2left":[
				{    

					"leftname":"手机通讯",
					"list3":[
						{
							"list3name":"手机"
						},
						{
							"list3name":"游戏手机"
						},
						{
							"list3name":"老人机"
						},
						{
							"list3name":"对讲机"
						},
						{
							"list3name":"以旧换新"
						},
						{
							"list3name":"手机维修"
						}
					]
				},
				{  
      
					"leftname":"运营商",
					"list3":[
						{
							"list3name":"合约机"
						},
						{
							"list3name":"选号码"
						},
						{
							"list3name":"固话宽带"
						},
						{
							"list3name":"办套餐"
						},
						{
							"list3name":"充话费/流量"
						},
						{
							"list3name":"中国电信"
						},
						{
							"list3name":"中国移动"
						},
						{
							"list3name":"中国联通"
						},
						{
							"list3name":"京东通信"
						},
						{
							"list3name":"170选号"
						},
						{
							"list3name":"上网卡"
						}
					]
				},
				{  
      
					"leftname":"手机配件",
					"list3":[
						{
							"list3name":"手机壳"
						},
						{
							"list3name":"贴膜"
						},
						{
							"list3name":"手机存储卡"
						},
						{
							"list3name":"充电器"
						},
						{
							"list3name":"手机耳机"
						},
						{
							"list3name":"创意配件"
						},
						{
							"list3name":"手机饰品"
						},
						{
							"list3name":"手机电池"
						},
						{
							"list3name":"苹果周边"
						},
						{
							"list3name":"移动电源"
						},
						{
							"list3name":"蓝牙耳机"
						},
						{
							"list3name":"手机支架"
						},
						{
							"list3name":"车载配件"
						},
						{
							"list3name":"拍照配件"
						}
					]
				},
				{  
    
					"leftname":"摄影摄像",
					"list3":[
						{
							"list3name":"单电/微单相机"
						},
						{
							"list3name":"单反相机"
						},
						{
							"list3name":"运动相机"
						},
						{
							"list3name":"摄像机"
						},
						{
							"list3name":"镜头"
						},
						{
							"list3name":"户外器材"
						},
						{
							"list3name":"影棚器材"
						},
						{
							"list3name":"冲印服务"
						},
						{
							"list3name":"数码相框"
						}
					]
				},
				{  
    
					"leftname":"数码配件",
					"list3":[
						{
							"list3name":"存储卡"
						},
						{
							"list3name":"三脚架/云台"
						},
						{
							"list3name":"相机包"
						},
						{
							"list3name":"滤镜"
						},
						{
							"list3name":"闪光灯/手柄"
						},
						{
							"list3name":"相机清洁/贴膜"
						},
						{
							"list3name":"机身附件"
						},
						{
							"list3name":"镜头附件"
						},
						{
							"list3name":"读卡器"
						},
						{
							"list3name":"支架"
						},
						{
							"list3name":"电池/充电器"
						}
					]
				},
				{  
      
					"leftname":"影音娱乐",
					"list3":[
						{
							"list3name":"耳机/耳麦"
						},
						{
							"list3name":"音箱/音响"
						},
						{
							"list3name":"智能音箱"
						},
						{
							"list3name":"便携/无线音箱"
						},
						{
							"list3name":"收音机"
						},
						{
							"list3name":"麦克风"
						},
						{
							"list3name":"MP3/MP4"
						},
						{
							"list3name":"专业音频"
						},
						{
							"list3name":"音频线"
						}
					]
				},
				{   
    
					"leftname":"智能设备",
					"list3":[
						{
							"list3name":"智能手环"
						},
						{
							"list3name":"智能手表"
						},
						{
							"list3name":"智能眼镜"
						},
						{
							"list3name":"智能机器人"
						},
						{
							"list3name":"运动跟踪器"
						},
						{
							"list3name":"健康监测"
						},
						{
							"list3name":"智能配饰"
						},
						{
							"list3name":"智能家居"
						},
						{
							"list3name":"体感车"
						},
						{
							"list3name":"无人机"
						}
					]
				},
				{  
              
					"leftname":"电子教育",
					"list3":[
						{
							"list3name":"学生平板"
						},
						{
							"list3name":"点读机/笔"
						},
						{
							"list3name":"早教益智"
						},
						{
							"list3name":"录音笔"
						},
						{
							"list3name":"电纸书"
						},
						{
							"list3name":"电子词典"
						},
						{
							"list3name":"复读机"
						},
						{
							"list3name":"翻译机"
						}
					]
				}
			]	
		},
		{
			"list1":"电脑办公",
			"list2top":[

				{
					"topname":"玩3C"
				},
				{
					"topname":"本周热卖"
				},
				{
					"topname":"企业采购"
				},
				{
					"topname":"GAME"
				},
				{
					"topname":"装机大师"
				},
				{
					"topname":"私人定制"
				}
			],
			"list2left":[
				{    
    
					"leftname":"电脑整机",
					"list3":[
						{
							"list3name":"笔记本"
						},
						{
							"list3name":"游戏本"
						},
						{
							"list3name":"平板电脑"
						},
						{
							"list3name":"平板电脑配件"
						},
						{
							"list3name":"台式机"
						},
						{
							"list3name":"一体机"
						},
						{
							"list3name":"服务器/工作站"
						},
						{
							"list3name":"笔记本配件"
						}
					]
				},
				{    
    
					"leftname":"电脑配件",
					"list3":[
						{
							"list3name":"显示器"
						},
						{
							"list3name":"CPU"
						},
						{
							"list3name":"主板"
						},
						{
							"list3name":"显卡"
						},
						{
							"list3name":"硬盘"
						},
						{
							"list3name":"内存"
						},
						{
							"list3name":"机箱"
						},
						{
							"list3name":"电源"
						},
						{
							"list3name":"散热器"
						},
						{
							"list3name":"显示器支架"
						},
						{
							"list3name":"刻录机/光驱"
						},
						{
							"list3name":"声卡/扩展卡"
						},
						{
							"list3name":"装机配件"
						},
						{
							"list3name":"SSD固态硬盘"
						},
						{
							"list3name":"组装电脑"
						},
						{
							"list3name":"USB分线器"
						}
					]
				},
				{    

					"leftname":"外设产品",
					"list3":[
						{
							"list3name":"鼠标"
						},
						{
							"list3name":"键盘"
						},
						{
							"list3name":"键鼠套装"
						},
						{
							"list3name":"网络仪表仪器"
						},
						{
							"list3name":"U盘"
						},
						{
							"list3name":"移动硬盘"
						},
						{
							"list3name":"鼠标垫"
						},
						{
							"list3name":"摄像头"
						},
						{
							"list3name":"线缆"
						},
						{
							"list3name":"手写板"
						},
						{
							"list3name":"硬盘盒"
						},
						{
							"list3name":"电脑工具"
						},
						{
							"list3name":"电脑清洁"
						},
						{
							"list3name":"UPS电源"
						},
						{
							"list3name":"插座"
						}
					]
				},
				{    

					"leftname":"游戏设备",
					"list3":[
						{
							"list3name":"游戏机"
						},
						{
							"list3name":"游戏耳机"
						},
						{
							"list3name":"手柄/方向盘"
						},
						{
							"list3name":"游戏软件"
						},
						{
							"list3name":"游戏周边"
						}
					]
				},
				{    
        
					"leftname":"网络产品",
					"list3":[
						{
							"list3name":"路由器"
						},
						{
							"list3name":"网络机顶盒"
						},
						{
							"list3name":"交换机"
						},
						{
							"list3name":"网络存储"
						},
						{
							"list3name":"网卡"
						},
						{
							"list3name":"4G/3G上网"
						},
						{
							"list3name":"网线"
						},
						{
							"list3name":"网络配件"
						}
					]
				},
				{    
    
					"leftname":"办公设备",
					"list3":[
						{
							"list3name":"投影机"
						},
						{
							"list3name":"投影配件"
						},
						{
							"list3name":"多功能一体机"
						},
						{
							"list3name":"打印机"
						},
						{
							"list3name":"传真设备"
						},
						{
							"list3name":"验钞/点钞机"
						},
						{
							"list3name":"扫描设备"
						},
						{
							"list3name":"复合机"
						},
						{
							"list3name":"碎纸机"
						},
						{
							"list3name":"考勤门禁"
						},
						{
							"list3name":"收银机"
						},
						{
							"list3name":"会议音频视频"
						},
						{
							"list3name":"保险柜"
						},
						{
							"list3name":"装订/封装机"
						},
						{
							"list3name":"安防监控"
						},
						{
							"list3name":"办公家具"
						},
						{
							"list3name":"白板"
						}
					]
				},
				{    
 
					"leftname":"文具",
					"list3":[
						{
							"list3name":"笔类"
						},
						{
							"list3name":"本册/便签"
						},
						{
							"list3name":"办公文具"
						},
						{
							"list3name":"文件收纳"
						},
						{
							"list3name":"学生文具"
						},
						{
							"list3name":"计算器"
						},
						{
							"list3name":"画具画材"
						},
						{
							"list3name":"财会用品"
						}
					]
				},
				{    

					"leftname":"耗材",
					"list3":[
						{
							"list3name":"硒鼓/墨粉"
						},
						{
							"list3name":"墨盒"
						},
						{
							"list3name":"色带"
						},
						{
							"list3name":"纸类"
						},
						{
							"list3name":"刻录光盘"
						}
					]
				},
				{    
    
					"leftname":"服务产品",
					"list3":[
						{
							"list3name":"延保服务"
						},
						{
							"list3name":"上门安装"
						},
						{
							"list3name":"维修保养"
						},
						{
							"list3name":"电脑软件"
						}
					]
				}
			]
		},
		{
			"list1":"家居/家具/家装/厨具",
			"list2top":[
				{
					"topname":"家电馆"
				},
				{
					"topname":"家电专卖店"
				},
				{
					"topname":"家电服务"
				},
				{
					"topname":"企业采购"
				},
				{
					"topname":"商用电器"
				}
			],
			"list2left":[
				{
					"leftname":"电视",
					"list3":[
						{
							"list3name":"超薄电视"
						},
						{
							"list3name":"全面屏电视"
						},
						{
							"list3name":"智能电视"
						},
						{
							"list3name":"OLED电视"
						},
						{
							"list3name":"曲面电视"
						},
						{
							"list3name":"4K超清电视"
						},
						{
							"list3name":"55英寸"
						},
						{
							"list3name":"65英寸"
						},
						{
							"list3name":"电视配件"
						}
					]
				},
				{    
    
					"leftname":"空调",
					"list3":[
						{
							"list3name":"空调挂机"
						},
						{
							"list3name":"空调柜机"
						},
						{
							"list3name":"精选推荐"
						},
						{
							"list3name":"中央空调"
						},
						{
							"list3name":"移动空调"
						},
						{
							"list3name":"省电空调"
						},
						{
							"list3name":"变频空调"
						},
						{
							"list3name":"以旧换新"
						}
					]
				},
				{    

					"leftname":"洗衣机",
					"list3":[
						{
							"list3name":"滚筒洗衣机"
						},
						{
							"list3name":"洗烘一体机"
						},
						{
							"list3name":"波轮洗衣机"
						},
						{
							"list3name":"迷你洗衣机"
						},
						{
							"list3name":"烘干机"
						},
						{
							"list3name":"洗衣机配件"
						}
					]
				},
				{    
        
					"leftname":"冰箱",
					"list3":[
						{
							"list3name":"多门"
						},
						{
							"list3name":"对开门"
						},
						{
							"list3name":"三门"
						},
						{
							"list3name":"双门"
						},
						{
							"list3name":"冷柜/冰吧"
						},
						{
							"list3name":"酒柜"
						},
						{
							"list3name":"冰箱配件"
						}
					]
				},
				{    
        
					"leftname":"厨卫大电",
					"list3":[
						{
							"list3name":"油烟机"
						},
						{
							"list3name":"燃气灶"
						},
						{
							"list3name":"烟灶套装"
						},
						{
							"list3name":"中集成灶"
						},
						{
							"list3name":"消毒柜"
						},
						{
							"list3name":"洗碗机"
						},
						{
							"list3name":"电热水器"
						},
						{
							"list3name":"燃气热水器"
						},
						{
							"list3name":"空气能热水器"
						},
						{
							"list3name":"太阳能热水器"
						},
						{
							"list3name":"嵌入式厨电"
						},
						{
							"list3name":"烟机灶具配件"
						}
					]
				},
				{    
        
					"leftname":"厨房小电",
					"list3":[
						{
							"list3name":"破壁机"
						},
						{
							"list3name":"电烤箱"
						},
						{
							"list3name":"电饭煲"
						},
						{
							"list3name":"电压力锅"
						},
						{
							"list3name":"电炖锅"
						},
						{
							"list3name":"豆浆机"
						},
						{
							"list3name":"料理机"
						},
						{
							"list3name":"咖啡机"
						},
						{
							"list3name":"电饼铛"
						},
						{
							"list3name":"榨汁机/原汁机"
						},
						{
							"list3name":"电水壶/热水瓶"
						},
						{
							"list3name":"微波炉"
						},
						{
							"list3name":"多用途锅"
						},
						{
							"list3name":"养生壶"
						},
						{
							"list3name":"电磁炉"
						},
						{
							"list3name":"面包机"
						},
						{
							"list3name":"空气炸锅"
						},
						{
							"list3name":"面条机"
						},
						{
							"list3name":"电陶炉"
						},
						{
							"list3name":"煮蛋器"
						},
						{
							"list3name":"电烧烤炉"
						}
					]
				},
				{    
        
					"leftname":"生活电器",
					"list3":[
						{
							"list3name":"电风扇"
						},
						{
							"list3name":"冷风扇"
						},
						{
							"list3name":"空气净化器"
						},
						{
							"list3name":"吸尘器"
						},
						{
							"list3name":"除螨仪"
						},
						{
							"list3name":"扫地机器人"
						},
						{
							"list3name":"除湿机"
						},
						{
							"list3name":"干衣机"
						},{
							"list3name":"加湿器"
						},
						{
							"list3name":"蒸汽拖把/拖地机"
						},
						{
							"list3name":"挂烫机/熨斗"
						},
						{
							"list3name":"电话机"
						},
						{
							"list3name":"饮水机"
						},
						{
							"list3name":"净水器"
						},
						{
							"list3name":"取暖电器"
						},
						{
							"list3name":"毛球修剪器"
						},
						{
							"list3name":"生活电器配件"
						}
					]
				},
				{    
        
					"leftname":"个户健康",
					"list3":[
						{
							"list3name":"剃须刀"
						},
						{
							"list3name":"电动牙刷"
						},
						{
							"list3name":"电吹风"
						},
						{
							"list3name":"美容器"
						},
						{
							"list3name":"洁面仪"
						},
						{
							"list3name":"按摩器"
						},
						{
							"list3name":"健康秤"
						},
						{
							"list3name":"卷/直发器"
						},
						{
							"list3name":"剃/脱毛器"
						},
						{
							"list3name":"理发器"
						},
						{
							"list3name":"足浴盆"
						},
						{
							"list3name":"足疗机"
						},
						{
							"list3name":"按摩椅"
						}
					]
				},
				{    
    
					"leftname":"视听影音",
					"list3":[
						{
							"list3name":"家庭影院"
						},
						{
							"list3name":"KTV音响"
						},
						{
							"list3name":"迷你音响"
						},
						{
							"list3name":"DVD"
						},
						{
							"list3name":"功放"
						},
						{
							"list3name":"回音壁"
						},
						{
							"list3name":"麦克风"
						}
					]
				}
			]
		},
		{
			"list1":"男装/女装/童装/内衣",
			"list2top":[

				{
					"topname":"玩3C"
				},
				{
					"topname":"手机频道"
				},
				{
					"topname":"网上营业厅"
				},
				{
					"topname":"配件选购中心"
				},
				{
					"topname":"智能数码"
				},
				{
					"topname":"影像Club"
				}
			],
			"list2left":[
				{    

					"leftname":"手机通讯",
					"list3":[
						{
							"list3name":"手机"
						},
						{
							"list3name":"游戏手机"
						},
						{
							"list3name":"老人机"
						},
						{
							"list3name":"对讲机"
						},
						{
							"list3name":"以旧换新"
						},
						{
							"list3name":"手机维修"
						}
					]
				},
				{  
      
					"leftname":"运营商",
					"list3":[
						{
							"list3name":"合约机"
						},
						{
							"list3name":"选号码"
						},
						{
							"list3name":"固话宽带"
						},
						{
							"list3name":"办套餐"
						},
						{
							"list3name":"充话费/流量"
						},
						{
							"list3name":"中国电信"
						},
						{
							"list3name":"中国移动"
						},
						{
							"list3name":"中国联通"
						},
						{
							"list3name":"京东通信"
						},
						{
							"list3name":"170选号"
						},
						{
							"list3name":"上网卡"
						}
					]
				},
				{  
      
					"leftname":"手机配件",
					"list3":[
						{
							"list3name":"手机壳"
						},
						{
							"list3name":"贴膜"
						},
						{
							"list3name":"手机存储卡"
						},
						{
							"list3name":"充电器"
						},
						{
							"list3name":"手机耳机"
						},
						{
							"list3name":"创意配件"
						},
						{
							"list3name":"手机饰品"
						},
						{
							"list3name":"手机电池"
						},
						{
							"list3name":"苹果周边"
						},
						{
							"list3name":"移动电源"
						},
						{
							"list3name":"蓝牙耳机"
						},
						{
							"list3name":"手机支架"
						},
						{
							"list3name":"车载配件"
						},
						{
							"list3name":"拍照配件"
						}
					]
				},
				{  
    
					"leftname":"摄影摄像",
					"list3":[
						{
							"list3name":"单电/微单相机"
						},
						{
							"list3name":"单反相机"
						},
						{
							"list3name":"运动相机"
						},
						{
							"list3name":"摄像机"
						},
						{
							"list3name":"镜头"
						},
						{
							"list3name":"户外器材"
						},
						{
							"list3name":"影棚器材"
						},
						{
							"list3name":"冲印服务"
						},
						{
							"list3name":"数码相框"
						}
					]
				},
				{  
    
					"leftname":"数码配件",
					"list3":[
						{
							"list3name":"存储卡"
						},
						{
							"list3name":"三脚架/云台"
						},
						{
							"list3name":"相机包"
						},
						{
							"list3name":"滤镜"
						},
						{
							"list3name":"闪光灯/手柄"
						},
						{
							"list3name":"相机清洁/贴膜"
						},
						{
							"list3name":"机身附件"
						},
						{
							"list3name":"镜头附件"
						},
						{
							"list3name":"读卡器"
						},
						{
							"list3name":"支架"
						},
						{
							"list3name":"电池/充电器"
						}
					]
				},
				{  
      
					"leftname":"影音娱乐",
					"list3":[
						{
							"list3name":"耳机/耳麦"
						},
						{
							"list3name":"音箱/音响"
						},
						{
							"list3name":"智能音箱"
						},
						{
							"list3name":"便携/无线音箱"
						},
						{
							"list3name":"收音机"
						},
						{
							"list3name":"麦克风"
						},
						{
							"list3name":"MP3/MP4"
						},
						{
							"list3name":"专业音频"
						},
						{
							"list3name":"音频线"
						}
					]
				},
				{   
    
					"leftname":"智能设备",
					"list3":[
						{
							"list3name":"智能手环"
						},
						{
							"list3name":"智能手表"
						},
						{
							"list3name":"智能眼镜"
						},
						{
							"list3name":"智能机器人"
						},
						{
							"list3name":"运动跟踪器"
						},
						{
							"list3name":"健康监测"
						},
						{
							"list3name":"智能配饰"
						},
						{
							"list3name":"智能家居"
						},
						{
							"list3name":"体感车"
						},
						{
							"list3name":"无人机"
						}
					]
				},
				{  
              
					"leftname":"电子教育",
					"list3":[
						{
							"list3name":"学生平板"
						},
						{
							"list3name":"点读机/笔"
						},
						{
							"list3name":"早教益智"
						},
						{
							"list3name":"录音笔"
						},
						{
							"list3name":"电纸书"
						},
						{
							"list3name":"电子词典"
						},
						{
							"list3name":"复读机"
						},
						{
							"list3name":"翻译机"
						}
					]
				}
			]	
		},
		{
			"list1":"美妆/个护清洁/宠物",
			"list2top":[

				{
					"topname":"玩3C"
				},
				{
					"topname":"本周热卖"
				},
				{
					"topname":"企业采购"
				},
				{
					"topname":"GAME"
				},
				{
					"topname":"装机大师"
				},
				{
					"topname":"私人定制"
				}
			],
			"list2left":[
				{    
    
					"leftname":"电脑整机",
					"list3":[
						{
							"list3name":"笔记本"
						},
						{
							"list3name":"游戏本"
						},
						{
							"list3name":"平板电脑"
						},
						{
							"list3name":"平板电脑配件"
						},
						{
							"list3name":"台式机"
						},
						{
							"list3name":"一体机"
						},
						{
							"list3name":"服务器/工作站"
						},
						{
							"list3name":"笔记本配件"
						}
					]
				},
				{    
    
					"leftname":"电脑配件",
					"list3":[
						{
							"list3name":"显示器"
						},
						{
							"list3name":"CPU"
						},
						{
							"list3name":"主板"
						},
						{
							"list3name":"显卡"
						},
						{
							"list3name":"硬盘"
						},
						{
							"list3name":"内存"
						},
						{
							"list3name":"机箱"
						},
						{
							"list3name":"电源"
						},
						{
							"list3name":"散热器"
						},
						{
							"list3name":"显示器支架"
						},
						{
							"list3name":"刻录机/光驱"
						},
						{
							"list3name":"声卡/扩展卡"
						},
						{
							"list3name":"装机配件"
						},
						{
							"list3name":"SSD固态硬盘"
						},
						{
							"list3name":"组装电脑"
						},
						{
							"list3name":"USB分线器"
						}
					]
				},
				{    

					"leftname":"外设产品",
					"list3":[
						{
							"list3name":"鼠标"
						},
						{
							"list3name":"键盘"
						},
						{
							"list3name":"键鼠套装"
						},
						{
							"list3name":"网络仪表仪器"
						},
						{
							"list3name":"U盘"
						},
						{
							"list3name":"移动硬盘"
						},
						{
							"list3name":"鼠标垫"
						},
						{
							"list3name":"摄像头"
						},
						{
							"list3name":"线缆"
						},
						{
							"list3name":"手写板"
						},
						{
							"list3name":"硬盘盒"
						},
						{
							"list3name":"电脑工具"
						},
						{
							"list3name":"电脑清洁"
						},
						{
							"list3name":"UPS电源"
						},
						{
							"list3name":"插座"
						}
					]
				},
				{    

					"leftname":"游戏设备",
					"list3":[
						{
							"list3name":"游戏机"
						},
						{
							"list3name":"游戏耳机"
						},
						{
							"list3name":"手柄/方向盘"
						},
						{
							"list3name":"游戏软件"
						},
						{
							"list3name":"游戏周边"
						}
					]
				},
				{    
        
					"leftname":"网络产品",
					"list3":[
						{
							"list3name":"路由器"
						},
						{
							"list3name":"网络机顶盒"
						},
						{
							"list3name":"交换机"
						},
						{
							"list3name":"网络存储"
						},
						{
							"list3name":"网卡"
						},
						{
							"list3name":"4G/3G上网"
						},
						{
							"list3name":"网线"
						},
						{
							"list3name":"网络配件"
						}
					]
				},
				{    
    
					"leftname":"办公设备",
					"list3":[
						{
							"list3name":"投影机"
						},
						{
							"list3name":"投影配件"
						},
						{
							"list3name":"多功能一体机"
						},
						{
							"list3name":"打印机"
						},
						{
							"list3name":"传真设备"
						},
						{
							"list3name":"验钞/点钞机"
						},
						{
							"list3name":"扫描设备"
						},
						{
							"list3name":"复合机"
						},
						{
							"list3name":"碎纸机"
						},
						{
							"list3name":"考勤门禁"
						},
						{
							"list3name":"收银机"
						},
						{
							"list3name":"会议音频视频"
						},
						{
							"list3name":"保险柜"
						},
						{
							"list3name":"装订/封装机"
						},
						{
							"list3name":"安防监控"
						},
						{
							"list3name":"办公家具"
						},
						{
							"list3name":"白板"
						}
					]
				},
				{    
 
					"leftname":"文具",
					"list3":[
						{
							"list3name":"笔类"
						},
						{
							"list3name":"本册/便签"
						},
						{
							"list3name":"办公文具"
						},
						{
							"list3name":"文件收纳"
						},
						{
							"list3name":"学生文具"
						},
						{
							"list3name":"计算器"
						},
						{
							"list3name":"画具画材"
						},
						{
							"list3name":"财会用品"
						}
					]
				},
				{    

					"leftname":"耗材",
					"list3":[
						{
							"list3name":"硒鼓/墨粉"
						},
						{
							"list3name":"墨盒"
						},
						{
							"list3name":"色带"
						},
						{
							"list3name":"纸类"
						},
						{
							"list3name":"刻录光盘"
						}
					]
				},
				{    
    
					"leftname":"服务产品",
					"list3":[
						{
							"list3name":"延保服务"
						},
						{
							"list3name":"上门安装"
						},
						{
							"list3name":"维修保养"
						},
						{
							"list3name":"电脑软件"
						}
					]
				}
			]
		},
		{
			"list1":"女鞋/箱包/钟表/珠宝",
			"list2top":[
				{
					"topname":"家电馆"
				},
				{
					"topname":"家电专卖店"
				},
				{
					"topname":"家电服务"
				},
				{
					"topname":"企业采购"
				},
				{
					"topname":"商用电器"
				}
			],
			"list2left":[
				{
					"leftname":"电视",
					"list3":[
						{
							"list3name":"超薄电视"
						},
						{
							"list3name":"全面屏电视"
						},
						{
							"list3name":"智能电视"
						},
						{
							"list3name":"OLED电视"
						},
						{
							"list3name":"曲面电视"
						},
						{
							"list3name":"4K超清电视"
						},
						{
							"list3name":"55英寸"
						},
						{
							"list3name":"65英寸"
						},
						{
							"list3name":"电视配件"
						}
					]
				},
				{    
    
					"leftname":"空调",
					"list3":[
						{
							"list3name":"空调挂机"
						},
						{
							"list3name":"空调柜机"
						},
						{
							"list3name":"精选推荐"
						},
						{
							"list3name":"中央空调"
						},
						{
							"list3name":"移动空调"
						},
						{
							"list3name":"省电空调"
						},
						{
							"list3name":"变频空调"
						},
						{
							"list3name":"以旧换新"
						}
					]
				},
				{    

					"leftname":"洗衣机",
					"list3":[
						{
							"list3name":"滚筒洗衣机"
						},
						{
							"list3name":"洗烘一体机"
						},
						{
							"list3name":"波轮洗衣机"
						},
						{
							"list3name":"迷你洗衣机"
						},
						{
							"list3name":"烘干机"
						},
						{
							"list3name":"洗衣机配件"
						}
					]
				},
				{    
        
					"leftname":"冰箱",
					"list3":[
						{
							"list3name":"多门"
						},
						{
							"list3name":"对开门"
						},
						{
							"list3name":"三门"
						},
						{
							"list3name":"双门"
						},
						{
							"list3name":"冷柜/冰吧"
						},
						{
							"list3name":"酒柜"
						},
						{
							"list3name":"冰箱配件"
						}
					]
				},
				{    
        
					"leftname":"厨卫大电",
					"list3":[
						{
							"list3name":"油烟机"
						},
						{
							"list3name":"燃气灶"
						},
						{
							"list3name":"烟灶套装"
						},
						{
							"list3name":"中集成灶"
						},
						{
							"list3name":"消毒柜"
						},
						{
							"list3name":"洗碗机"
						},
						{
							"list3name":"电热水器"
						},
						{
							"list3name":"燃气热水器"
						},
						{
							"list3name":"空气能热水器"
						},
						{
							"list3name":"太阳能热水器"
						},
						{
							"list3name":"嵌入式厨电"
						},
						{
							"list3name":"烟机灶具配件"
						}
					]
				},
				{    
        
					"leftname":"厨房小电",
					"list3":[
						{
							"list3name":"破壁机"
						},
						{
							"list3name":"电烤箱"
						},
						{
							"list3name":"电饭煲"
						},
						{
							"list3name":"电压力锅"
						},
						{
							"list3name":"电炖锅"
						},
						{
							"list3name":"豆浆机"
						},
						{
							"list3name":"料理机"
						},
						{
							"list3name":"咖啡机"
						},
						{
							"list3name":"电饼铛"
						},
						{
							"list3name":"榨汁机/原汁机"
						},
						{
							"list3name":"电水壶/热水瓶"
						},
						{
							"list3name":"微波炉"
						},
						{
							"list3name":"多用途锅"
						},
						{
							"list3name":"养生壶"
						},
						{
							"list3name":"电磁炉"
						},
						{
							"list3name":"面包机"
						},
						{
							"list3name":"空气炸锅"
						},
						{
							"list3name":"面条机"
						},
						{
							"list3name":"电陶炉"
						},
						{
							"list3name":"煮蛋器"
						},
						{
							"list3name":"电烧烤炉"
						}
					]
				},
				{    
        
					"leftname":"生活电器",
					"list3":[
						{
							"list3name":"电风扇"
						},
						{
							"list3name":"冷风扇"
						},
						{
							"list3name":"空气净化器"
						},
						{
							"list3name":"吸尘器"
						},
						{
							"list3name":"除螨仪"
						},
						{
							"list3name":"扫地机器人"
						},
						{
							"list3name":"除湿机"
						},
						{
							"list3name":"干衣机"
						},{
							"list3name":"加湿器"
						},
						{
							"list3name":"蒸汽拖把/拖地机"
						},
						{
							"list3name":"挂烫机/熨斗"
						},
						{
							"list3name":"电话机"
						},
						{
							"list3name":"饮水机"
						},
						{
							"list3name":"净水器"
						},
						{
							"list3name":"取暖电器"
						},
						{
							"list3name":"毛球修剪器"
						},
						{
							"list3name":"生活电器配件"
						}
					]
				},
				{    
        
					"leftname":"个户健康",
					"list3":[
						{
							"list3name":"剃须刀"
						},
						{
							"list3name":"电动牙刷"
						},
						{
							"list3name":"电吹风"
						},
						{
							"list3name":"美容器"
						},
						{
							"list3name":"洁面仪"
						},
						{
							"list3name":"按摩器"
						},
						{
							"list3name":"健康秤"
						},
						{
							"list3name":"卷/直发器"
						},
						{
							"list3name":"剃/脱毛器"
						},
						{
							"list3name":"理发器"
						},
						{
							"list3name":"足浴盆"
						},
						{
							"list3name":"足疗机"
						},
						{
							"list3name":"按摩椅"
						}
					]
				},
				{    
    
					"leftname":"视听影音",
					"list3":[
						{
							"list3name":"家庭影院"
						},
						{
							"list3name":"KTV音响"
						},
						{
							"list3name":"迷你音响"
						},
						{
							"list3name":"DVD"
						},
						{
							"list3name":"功放"
						},
						{
							"list3name":"回音壁"
						},
						{
							"list3name":"麦克风"
						}
					]
				}
			]
		},
		{
			"list1":"男鞋/运动/户外",
			"list2top":[

				{
					"topname":"玩3C"
				},
				{
					"topname":"手机频道"
				},
				{
					"topname":"网上营业厅"
				},
				{
					"topname":"配件选购中心"
				},
				{
					"topname":"智能数码"
				},
				{
					"topname":"影像Club"
				}
			],
			"list2left":[
				{    

					"leftname":"手机通讯",
					"list3":[
						{
							"list3name":"手机"
						},
						{
							"list3name":"游戏手机"
						},
						{
							"list3name":"老人机"
						},
						{
							"list3name":"对讲机"
						},
						{
							"list3name":"以旧换新"
						},
						{
							"list3name":"手机维修"
						}
					]
				},
				{  
      
					"leftname":"运营商",
					"list3":[
						{
							"list3name":"合约机"
						},
						{
							"list3name":"选号码"
						},
						{
							"list3name":"固话宽带"
						},
						{
							"list3name":"办套餐"
						},
						{
							"list3name":"充话费/流量"
						},
						{
							"list3name":"中国电信"
						},
						{
							"list3name":"中国移动"
						},
						{
							"list3name":"中国联通"
						},
						{
							"list3name":"京东通信"
						},
						{
							"list3name":"170选号"
						},
						{
							"list3name":"上网卡"
						}
					]
				},
				{  
      
					"leftname":"手机配件",
					"list3":[
						{
							"list3name":"手机壳"
						},
						{
							"list3name":"贴膜"
						},
						{
							"list3name":"手机存储卡"
						},
						{
							"list3name":"充电器"
						},
						{
							"list3name":"手机耳机"
						},
						{
							"list3name":"创意配件"
						},
						{
							"list3name":"手机饰品"
						},
						{
							"list3name":"手机电池"
						},
						{
							"list3name":"苹果周边"
						},
						{
							"list3name":"移动电源"
						},
						{
							"list3name":"蓝牙耳机"
						},
						{
							"list3name":"手机支架"
						},
						{
							"list3name":"车载配件"
						},
						{
							"list3name":"拍照配件"
						}
					]
				},
				{  
    
					"leftname":"摄影摄像",
					"list3":[
						{
							"list3name":"单电/微单相机"
						},
						{
							"list3name":"单反相机"
						},
						{
							"list3name":"运动相机"
						},
						{
							"list3name":"摄像机"
						},
						{
							"list3name":"镜头"
						},
						{
							"list3name":"户外器材"
						},
						{
							"list3name":"影棚器材"
						},
						{
							"list3name":"冲印服务"
						},
						{
							"list3name":"数码相框"
						}
					]
				},
				{  
    
					"leftname":"数码配件",
					"list3":[
						{
							"list3name":"存储卡"
						},
						{
							"list3name":"三脚架/云台"
						},
						{
							"list3name":"相机包"
						},
						{
							"list3name":"滤镜"
						},
						{
							"list3name":"闪光灯/手柄"
						},
						{
							"list3name":"相机清洁/贴膜"
						},
						{
							"list3name":"机身附件"
						},
						{
							"list3name":"镜头附件"
						},
						{
							"list3name":"读卡器"
						},
						{
							"list3name":"支架"
						},
						{
							"list3name":"电池/充电器"
						}
					]
				},
				{  
      
					"leftname":"影音娱乐",
					"list3":[
						{
							"list3name":"耳机/耳麦"
						},
						{
							"list3name":"音箱/音响"
						},
						{
							"list3name":"智能音箱"
						},
						{
							"list3name":"便携/无线音箱"
						},
						{
							"list3name":"收音机"
						},
						{
							"list3name":"麦克风"
						},
						{
							"list3name":"MP3/MP4"
						},
						{
							"list3name":"专业音频"
						},
						{
							"list3name":"音频线"
						}
					]
				},
				{   
    
					"leftname":"智能设备",
					"list3":[
						{
							"list3name":"智能手环"
						},
						{
							"list3name":"智能手表"
						},
						{
							"list3name":"智能眼镜"
						},
						{
							"list3name":"智能机器人"
						},
						{
							"list3name":"运动跟踪器"
						},
						{
							"list3name":"健康监测"
						},
						{
							"list3name":"智能配饰"
						},
						{
							"list3name":"智能家居"
						},
						{
							"list3name":"体感车"
						},
						{
							"list3name":"无人机"
						}
					]
				},
				{  
              
					"leftname":"电子教育",
					"list3":[
						{
							"list3name":"学生平板"
						},
						{
							"list3name":"点读机/笔"
						},
						{
							"list3name":"早教益智"
						},
						{
							"list3name":"录音笔"
						},
						{
							"list3name":"电纸书"
						},
						{
							"list3name":"电子词典"
						},
						{
							"list3name":"复读机"
						},
						{
							"list3name":"翻译机"
						}
					]
				}
			]	
		},
		{
			"list1":"房产/汽车/汽车用品",
			"list2top":[

				{
					"topname":"玩3C"
				},
				{
					"topname":"本周热卖"
				},
				{
					"topname":"企业采购"
				},
				{
					"topname":"GAME"
				},
				{
					"topname":"装机大师"
				},
				{
					"topname":"私人定制"
				}
			],
			"list2left":[
				{    
    
					"leftname":"电脑整机",
					"list3":[
						{
							"list3name":"笔记本"
						},
						{
							"list3name":"游戏本"
						},
						{
							"list3name":"平板电脑"
						},
						{
							"list3name":"平板电脑配件"
						},
						{
							"list3name":"台式机"
						},
						{
							"list3name":"一体机"
						},
						{
							"list3name":"服务器/工作站"
						},
						{
							"list3name":"笔记本配件"
						}
					]
				},
				{    
    
					"leftname":"电脑配件",
					"list3":[
						{
							"list3name":"显示器"
						},
						{
							"list3name":"CPU"
						},
						{
							"list3name":"主板"
						},
						{
							"list3name":"显卡"
						},
						{
							"list3name":"硬盘"
						},
						{
							"list3name":"内存"
						},
						{
							"list3name":"机箱"
						},
						{
							"list3name":"电源"
						},
						{
							"list3name":"散热器"
						},
						{
							"list3name":"显示器支架"
						},
						{
							"list3name":"刻录机/光驱"
						},
						{
							"list3name":"声卡/扩展卡"
						},
						{
							"list3name":"装机配件"
						},
						{
							"list3name":"SSD固态硬盘"
						},
						{
							"list3name":"组装电脑"
						},
						{
							"list3name":"USB分线器"
						}
					]
				},
				{    

					"leftname":"外设产品",
					"list3":[
						{
							"list3name":"鼠标"
						},
						{
							"list3name":"键盘"
						},
						{
							"list3name":"键鼠套装"
						},
						{
							"list3name":"网络仪表仪器"
						},
						{
							"list3name":"U盘"
						},
						{
							"list3name":"移动硬盘"
						},
						{
							"list3name":"鼠标垫"
						},
						{
							"list3name":"摄像头"
						},
						{
							"list3name":"线缆"
						},
						{
							"list3name":"手写板"
						},
						{
							"list3name":"硬盘盒"
						},
						{
							"list3name":"电脑工具"
						},
						{
							"list3name":"电脑清洁"
						},
						{
							"list3name":"UPS电源"
						},
						{
							"list3name":"插座"
						}
					]
				},
				{    

					"leftname":"游戏设备",
					"list3":[
						{
							"list3name":"游戏机"
						},
						{
							"list3name":"游戏耳机"
						},
						{
							"list3name":"手柄/方向盘"
						},
						{
							"list3name":"游戏软件"
						},
						{
							"list3name":"游戏周边"
						}
					]
				},
				{    
        
					"leftname":"网络产品",
					"list3":[
						{
							"list3name":"路由器"
						},
						{
							"list3name":"网络机顶盒"
						},
						{
							"list3name":"交换机"
						},
						{
							"list3name":"网络存储"
						},
						{
							"list3name":"网卡"
						},
						{
							"list3name":"4G/3G上网"
						},
						{
							"list3name":"网线"
						},
						{
							"list3name":"网络配件"
						}
					]
				},
				{    
    
					"leftname":"办公设备",
					"list3":[
						{
							"list3name":"投影机"
						},
						{
							"list3name":"投影配件"
						},
						{
							"list3name":"多功能一体机"
						},
						{
							"list3name":"打印机"
						},
						{
							"list3name":"传真设备"
						},
						{
							"list3name":"验钞/点钞机"
						},
						{
							"list3name":"扫描设备"
						},
						{
							"list3name":"复合机"
						},
						{
							"list3name":"碎纸机"
						},
						{
							"list3name":"考勤门禁"
						},
						{
							"list3name":"收银机"
						},
						{
							"list3name":"会议音频视频"
						},
						{
							"list3name":"保险柜"
						},
						{
							"list3name":"装订/封装机"
						},
						{
							"list3name":"安防监控"
						},
						{
							"list3name":"办公家具"
						},
						{
							"list3name":"白板"
						}
					]
				},
				{    
 
					"leftname":"文具",
					"list3":[
						{
							"list3name":"笔类"
						},
						{
							"list3name":"本册/便签"
						},
						{
							"list3name":"办公文具"
						},
						{
							"list3name":"文件收纳"
						},
						{
							"list3name":"学生文具"
						},
						{
							"list3name":"计算器"
						},
						{
							"list3name":"画具画材"
						},
						{
							"list3name":"财会用品"
						}
					]
				},
				{    

					"leftname":"耗材",
					"list3":[
						{
							"list3name":"硒鼓/墨粉"
						},
						{
							"list3name":"墨盒"
						},
						{
							"list3name":"色带"
						},
						{
							"list3name":"纸类"
						},
						{
							"list3name":"刻录光盘"
						}
					]
				},
				{    
    
					"leftname":"服务产品",
					"list3":[
						{
							"list3name":"延保服务"
						},
						{
							"list3name":"上门安装"
						},
						{
							"list3name":"维修保养"
						},
						{
							"list3name":"电脑软件"
						}
					]
				}
			]
		},
		{
			"list1":"母婴/玩具乐器",
			"list2top":[
				{
					"topname":"家电馆"
				},
				{
					"topname":"家电专卖店"
				},
				{
					"topname":"家电服务"
				},
				{
					"topname":"企业采购"
				},
				{
					"topname":"商用电器"
				}
			],
			"list2left":[
				{
					"leftname":"电视",
					"list3":[
						{
							"list3name":"超薄电视"
						},
						{
							"list3name":"全面屏电视"
						},
						{
							"list3name":"智能电视"
						},
						{
							"list3name":"OLED电视"
						},
						{
							"list3name":"曲面电视"
						},
						{
							"list3name":"4K超清电视"
						},
						{
							"list3name":"55英寸"
						},
						{
							"list3name":"65英寸"
						},
						{
							"list3name":"电视配件"
						}
					]
				},
				{    
    
					"leftname":"空调",
					"list3":[
						{
							"list3name":"空调挂机"
						},
						{
							"list3name":"空调柜机"
						},
						{
							"list3name":"精选推荐"
						},
						{
							"list3name":"中央空调"
						},
						{
							"list3name":"移动空调"
						},
						{
							"list3name":"省电空调"
						},
						{
							"list3name":"变频空调"
						},
						{
							"list3name":"以旧换新"
						}
					]
				},
				{    

					"leftname":"洗衣机",
					"list3":[
						{
							"list3name":"滚筒洗衣机"
						},
						{
							"list3name":"洗烘一体机"
						},
						{
							"list3name":"波轮洗衣机"
						},
						{
							"list3name":"迷你洗衣机"
						},
						{
							"list3name":"烘干机"
						},
						{
							"list3name":"洗衣机配件"
						}
					]
				},
				{    
        
					"leftname":"冰箱",
					"list3":[
						{
							"list3name":"多门"
						},
						{
							"list3name":"对开门"
						},
						{
							"list3name":"三门"
						},
						{
							"list3name":"双门"
						},
						{
							"list3name":"冷柜/冰吧"
						},
						{
							"list3name":"酒柜"
						},
						{
							"list3name":"冰箱配件"
						}
					]
				},
				{    
        
					"leftname":"厨卫大电",
					"list3":[
						{
							"list3name":"油烟机"
						},
						{
							"list3name":"燃气灶"
						},
						{
							"list3name":"烟灶套装"
						},
						{
							"list3name":"中集成灶"
						},
						{
							"list3name":"消毒柜"
						},
						{
							"list3name":"洗碗机"
						},
						{
							"list3name":"电热水器"
						},
						{
							"list3name":"燃气热水器"
						},
						{
							"list3name":"空气能热水器"
						},
						{
							"list3name":"太阳能热水器"
						},
						{
							"list3name":"嵌入式厨电"
						},
						{
							"list3name":"烟机灶具配件"
						}
					]
				},
				{    
        
					"leftname":"厨房小电",
					"list3":[
						{
							"list3name":"破壁机"
						},
						{
							"list3name":"电烤箱"
						},
						{
							"list3name":"电饭煲"
						},
						{
							"list3name":"电压力锅"
						},
						{
							"list3name":"电炖锅"
						},
						{
							"list3name":"豆浆机"
						},
						{
							"list3name":"料理机"
						},
						{
							"list3name":"咖啡机"
						},
						{
							"list3name":"电饼铛"
						},
						{
							"list3name":"榨汁机/原汁机"
						},
						{
							"list3name":"电水壶/热水瓶"
						},
						{
							"list3name":"微波炉"
						},
						{
							"list3name":"多用途锅"
						},
						{
							"list3name":"养生壶"
						},
						{
							"list3name":"电磁炉"
						},
						{
							"list3name":"面包机"
						},
						{
							"list3name":"空气炸锅"
						},
						{
							"list3name":"面条机"
						},
						{
							"list3name":"电陶炉"
						},
						{
							"list3name":"煮蛋器"
						},
						{
							"list3name":"电烧烤炉"
						}
					]
				},
				{    
        
					"leftname":"生活电器",
					"list3":[
						{
							"list3name":"电风扇"
						},
						{
							"list3name":"冷风扇"
						},
						{
							"list3name":"空气净化器"
						},
						{
							"list3name":"吸尘器"
						},
						{
							"list3name":"除螨仪"
						},
						{
							"list3name":"扫地机器人"
						},
						{
							"list3name":"除湿机"
						},
						{
							"list3name":"干衣机"
						},{
							"list3name":"加湿器"
						},
						{
							"list3name":"蒸汽拖把/拖地机"
						},
						{
							"list3name":"挂烫机/熨斗"
						},
						{
							"list3name":"电话机"
						},
						{
							"list3name":"饮水机"
						},
						{
							"list3name":"净水器"
						},
						{
							"list3name":"取暖电器"
						},
						{
							"list3name":"毛球修剪器"
						},
						{
							"list3name":"生活电器配件"
						}
					]
				},
				{    
        
					"leftname":"个户健康",
					"list3":[
						{
							"list3name":"剃须刀"
						},
						{
							"list3name":"电动牙刷"
						},
						{
							"list3name":"电吹风"
						},
						{
							"list3name":"美容器"
						},
						{
							"list3name":"洁面仪"
						},
						{
							"list3name":"按摩器"
						},
						{
							"list3name":"健康秤"
						},
						{
							"list3name":"卷/直发器"
						},
						{
							"list3name":"剃/脱毛器"
						},
						{
							"list3name":"理发器"
						},
						{
							"list3name":"足浴盆"
						},
						{
							"list3name":"足疗机"
						},
						{
							"list3name":"按摩椅"
						}
					]
				},
				{    
    
					"leftname":"视听影音",
					"list3":[
						{
							"list3name":"家庭影院"
						},
						{
							"list3name":"KTV音响"
						},
						{
							"list3name":"迷你音响"
						},
						{
							"list3name":"DVD"
						},
						{
							"list3name":"功放"
						},
						{
							"list3name":"回音壁"
						},
						{
							"list3name":"麦克风"
						}
					]
				}
			]
		},
		{
			"list1":"食品/酒类/生鲜/特产",
			"list2top":[

				{
					"topname":"玩3C"
				},
				{
					"topname":"手机频道"
				},
				{
					"topname":"网上营业厅"
				},
				{
					"topname":"配件选购中心"
				},
				{
					"topname":"智能数码"
				},
				{
					"topname":"影像Club"
				}
			],
			"list2left":[
				{    

					"leftname":"手机通讯",
					"list3":[
						{
							"list3name":"手机"
						},
						{
							"list3name":"游戏手机"
						},
						{
							"list3name":"老人机"
						},
						{
							"list3name":"对讲机"
						},
						{
							"list3name":"以旧换新"
						},
						{
							"list3name":"手机维修"
						}
					]
				},
				{  
      
					"leftname":"运营商",
					"list3":[
						{
							"list3name":"合约机"
						},
						{
							"list3name":"选号码"
						},
						{
							"list3name":"固话宽带"
						},
						{
							"list3name":"办套餐"
						},
						{
							"list3name":"充话费/流量"
						},
						{
							"list3name":"中国电信"
						},
						{
							"list3name":"中国移动"
						},
						{
							"list3name":"中国联通"
						},
						{
							"list3name":"京东通信"
						},
						{
							"list3name":"170选号"
						},
						{
							"list3name":"上网卡"
						}
					]
				},
				{  
      
					"leftname":"手机配件",
					"list3":[
						{
							"list3name":"手机壳"
						},
						{
							"list3name":"贴膜"
						},
						{
							"list3name":"手机存储卡"
						},
						{
							"list3name":"充电器"
						},
						{
							"list3name":"手机耳机"
						},
						{
							"list3name":"创意配件"
						},
						{
							"list3name":"手机饰品"
						},
						{
							"list3name":"手机电池"
						},
						{
							"list3name":"苹果周边"
						},
						{
							"list3name":"移动电源"
						},
						{
							"list3name":"蓝牙耳机"
						},
						{
							"list3name":"手机支架"
						},
						{
							"list3name":"车载配件"
						},
						{
							"list3name":"拍照配件"
						}
					]
				},
				{  
    
					"leftname":"摄影摄像",
					"list3":[
						{
							"list3name":"单电/微单相机"
						},
						{
							"list3name":"单反相机"
						},
						{
							"list3name":"运动相机"
						},
						{
							"list3name":"摄像机"
						},
						{
							"list3name":"镜头"
						},
						{
							"list3name":"户外器材"
						},
						{
							"list3name":"影棚器材"
						},
						{
							"list3name":"冲印服务"
						},
						{
							"list3name":"数码相框"
						}
					]
				},
				{  
    
					"leftname":"数码配件",
					"list3":[
						{
							"list3name":"存储卡"
						},
						{
							"list3name":"三脚架/云台"
						},
						{
							"list3name":"相机包"
						},
						{
							"list3name":"滤镜"
						},
						{
							"list3name":"闪光灯/手柄"
						},
						{
							"list3name":"相机清洁/贴膜"
						},
						{
							"list3name":"机身附件"
						},
						{
							"list3name":"镜头附件"
						},
						{
							"list3name":"读卡器"
						},
						{
							"list3name":"支架"
						},
						{
							"list3name":"电池/充电器"
						}
					]
				},
				{  
      
					"leftname":"影音娱乐",
					"list3":[
						{
							"list3name":"耳机/耳麦"
						},
						{
							"list3name":"音箱/音响"
						},
						{
							"list3name":"智能音箱"
						},
						{
							"list3name":"便携/无线音箱"
						},
						{
							"list3name":"收音机"
						},
						{
							"list3name":"麦克风"
						},
						{
							"list3name":"MP3/MP4"
						},
						{
							"list3name":"专业音频"
						},
						{
							"list3name":"音频线"
						}
					]
				},
				{   
    
					"leftname":"智能设备",
					"list3":[
						{
							"list3name":"智能手环"
						},
						{
							"list3name":"智能手表"
						},
						{
							"list3name":"智能眼镜"
						},
						{
							"list3name":"智能机器人"
						},
						{
							"list3name":"运动跟踪器"
						},
						{
							"list3name":"健康监测"
						},
						{
							"list3name":"智能配饰"
						},
						{
							"list3name":"智能家居"
						},
						{
							"list3name":"体感车"
						},
						{
							"list3name":"无人机"
						}
					]
				},
				{  
              
					"leftname":"电子教育",
					"list3":[
						{
							"list3name":"学生平板"
						},
						{
							"list3name":"点读机/笔"
						},
						{
							"list3name":"早教益智"
						},
						{
							"list3name":"录音笔"
						},
						{
							"list3name":"电纸书"
						},
						{
							"list3name":"电子词典"
						},
						{
							"list3name":"复读机"
						},
						{
							"list3name":"翻译机"
						}
					]
				}
			]	
		},
		{
			"list1":"艺术/礼品鲜花/农资绿植",
			"list2top":[

				{
					"topname":"玩3C"
				},
				{
					"topname":"本周热卖"
				},
				{
					"topname":"企业采购"
				},
				{
					"topname":"GAME"
				},
				{
					"topname":"装机大师"
				},
				{
					"topname":"私人定制"
				}
			],
			"list2left":[
				{    
    
					"leftname":"电脑整机",
					"list3":[
						{
							"list3name":"笔记本"
						},
						{
							"list3name":"游戏本"
						},
						{
							"list3name":"平板电脑"
						},
						{
							"list3name":"平板电脑配件"
						},
						{
							"list3name":"台式机"
						},
						{
							"list3name":"一体机"
						},
						{
							"list3name":"服务器/工作站"
						},
						{
							"list3name":"笔记本配件"
						}
					]
				},
				{    
    
					"leftname":"电脑配件",
					"list3":[
						{
							"list3name":"显示器"
						},
						{
							"list3name":"CPU"
						},
						{
							"list3name":"主板"
						},
						{
							"list3name":"显卡"
						},
						{
							"list3name":"硬盘"
						},
						{
							"list3name":"内存"
						},
						{
							"list3name":"机箱"
						},
						{
							"list3name":"电源"
						},
						{
							"list3name":"散热器"
						},
						{
							"list3name":"显示器支架"
						},
						{
							"list3name":"刻录机/光驱"
						},
						{
							"list3name":"声卡/扩展卡"
						},
						{
							"list3name":"装机配件"
						},
						{
							"list3name":"SSD固态硬盘"
						},
						{
							"list3name":"组装电脑"
						},
						{
							"list3name":"USB分线器"
						}
					]
				},
				{    

					"leftname":"外设产品",
					"list3":[
						{
							"list3name":"鼠标"
						},
						{
							"list3name":"键盘"
						},
						{
							"list3name":"键鼠套装"
						},
						{
							"list3name":"网络仪表仪器"
						},
						{
							"list3name":"U盘"
						},
						{
							"list3name":"移动硬盘"
						},
						{
							"list3name":"鼠标垫"
						},
						{
							"list3name":"摄像头"
						},
						{
							"list3name":"线缆"
						},
						{
							"list3name":"手写板"
						},
						{
							"list3name":"硬盘盒"
						},
						{
							"list3name":"电脑工具"
						},
						{
							"list3name":"电脑清洁"
						},
						{
							"list3name":"UPS电源"
						},
						{
							"list3name":"插座"
						}
					]
				},
				{    

					"leftname":"游戏设备",
					"list3":[
						{
							"list3name":"游戏机"
						},
						{
							"list3name":"游戏耳机"
						},
						{
							"list3name":"手柄/方向盘"
						},
						{
							"list3name":"游戏软件"
						},
						{
							"list3name":"游戏周边"
						}
					]
				},
				{    
        
					"leftname":"网络产品",
					"list3":[
						{
							"list3name":"路由器"
						},
						{
							"list3name":"网络机顶盒"
						},
						{
							"list3name":"交换机"
						},
						{
							"list3name":"网络存储"
						},
						{
							"list3name":"网卡"
						},
						{
							"list3name":"4G/3G上网"
						},
						{
							"list3name":"网线"
						},
						{
							"list3name":"网络配件"
						}
					]
				},
				{    
    
					"leftname":"办公设备",
					"list3":[
						{
							"list3name":"投影机"
						},
						{
							"list3name":"投影配件"
						},
						{
							"list3name":"多功能一体机"
						},
						{
							"list3name":"打印机"
						},
						{
							"list3name":"传真设备"
						},
						{
							"list3name":"验钞/点钞机"
						},
						{
							"list3name":"扫描设备"
						},
						{
							"list3name":"复合机"
						},
						{
							"list3name":"碎纸机"
						},
						{
							"list3name":"考勤门禁"
						},
						{
							"list3name":"收银机"
						},
						{
							"list3name":"会议音频视频"
						},
						{
							"list3name":"保险柜"
						},
						{
							"list3name":"装订/封装机"
						},
						{
							"list3name":"安防监控"
						},
						{
							"list3name":"办公家具"
						},
						{
							"list3name":"白板"
						}
					]
				},
				{    
 
					"leftname":"文具",
					"list3":[
						{
							"list3name":"笔类"
						},
						{
							"list3name":"本册/便签"
						},
						{
							"list3name":"办公文具"
						},
						{
							"list3name":"文件收纳"
						},
						{
							"list3name":"学生文具"
						},
						{
							"list3name":"计算器"
						},
						{
							"list3name":"画具画材"
						},
						{
							"list3name":"财会用品"
						}
					]
				},
				{    

					"leftname":"耗材",
					"list3":[
						{
							"list3name":"硒鼓/墨粉"
						},
						{
							"list3name":"墨盒"
						},
						{
							"list3name":"色带"
						},
						{
							"list3name":"纸类"
						},
						{
							"list3name":"刻录光盘"
						}
					]
				},
				{    
    
					"leftname":"服务产品",
					"list3":[
						{
							"list3name":"延保服务"
						},
						{
							"list3name":"上门安装"
						},
						{
							"list3name":"维修保养"
						},
						{
							"list3name":"电脑软件"
						}
					]
				}
			]
		},
		{
			"list1":"医药保健/计生情趣",
			"list2top":[
				{
					"topname":"家电馆"
				},
				{
					"topname":"家电专卖店"
				},
				{
					"topname":"家电服务"
				},
				{
					"topname":"企业采购"
				},
				{
					"topname":"商用电器"
				}
			],
			"list2left":[
				{
					"leftname":"电视",
					"list3":[
						{
							"list3name":"超薄电视"
						},
						{
							"list3name":"全面屏电视"
						},
						{
							"list3name":"智能电视"
						},
						{
							"list3name":"OLED电视"
						},
						{
							"list3name":"曲面电视"
						},
						{
							"list3name":"4K超清电视"
						},
						{
							"list3name":"55英寸"
						},
						{
							"list3name":"65英寸"
						},
						{
							"list3name":"电视配件"
						}
					]
				},
				{    
    
					"leftname":"空调",
					"list3":[
						{
							"list3name":"空调挂机"
						},
						{
							"list3name":"空调柜机"
						},
						{
							"list3name":"精选推荐"
						},
						{
							"list3name":"中央空调"
						},
						{
							"list3name":"移动空调"
						},
						{
							"list3name":"省电空调"
						},
						{
							"list3name":"变频空调"
						},
						{
							"list3name":"以旧换新"
						}
					]
				},
				{    

					"leftname":"洗衣机",
					"list3":[
						{
							"list3name":"滚筒洗衣机"
						},
						{
							"list3name":"洗烘一体机"
						},
						{
							"list3name":"波轮洗衣机"
						},
						{
							"list3name":"迷你洗衣机"
						},
						{
							"list3name":"烘干机"
						},
						{
							"list3name":"洗衣机配件"
						}
					]
				},
				{    
        
					"leftname":"冰箱",
					"list3":[
						{
							"list3name":"多门"
						},
						{
							"list3name":"对开门"
						},
						{
							"list3name":"三门"
						},
						{
							"list3name":"双门"
						},
						{
							"list3name":"冷柜/冰吧"
						},
						{
							"list3name":"酒柜"
						},
						{
							"list3name":"冰箱配件"
						}
					]
				},
				{    
        
					"leftname":"厨卫大电",
					"list3":[
						{
							"list3name":"油烟机"
						},
						{
							"list3name":"燃气灶"
						},
						{
							"list3name":"烟灶套装"
						},
						{
							"list3name":"中集成灶"
						},
						{
							"list3name":"消毒柜"
						},
						{
							"list3name":"洗碗机"
						},
						{
							"list3name":"电热水器"
						},
						{
							"list3name":"燃气热水器"
						},
						{
							"list3name":"空气能热水器"
						},
						{
							"list3name":"太阳能热水器"
						},
						{
							"list3name":"嵌入式厨电"
						},
						{
							"list3name":"烟机灶具配件"
						}
					]
				},
				{    
        
					"leftname":"厨房小电",
					"list3":[
						{
							"list3name":"破壁机"
						},
						{
							"list3name":"电烤箱"
						},
						{
							"list3name":"电饭煲"
						},
						{
							"list3name":"电压力锅"
						},
						{
							"list3name":"电炖锅"
						},
						{
							"list3name":"豆浆机"
						},
						{
							"list3name":"料理机"
						},
						{
							"list3name":"咖啡机"
						},
						{
							"list3name":"电饼铛"
						},
						{
							"list3name":"榨汁机/原汁机"
						},
						{
							"list3name":"电水壶/热水瓶"
						},
						{
							"list3name":"微波炉"
						},
						{
							"list3name":"多用途锅"
						},
						{
							"list3name":"养生壶"
						},
						{
							"list3name":"电磁炉"
						},
						{
							"list3name":"面包机"
						},
						{
							"list3name":"空气炸锅"
						},
						{
							"list3name":"面条机"
						},
						{
							"list3name":"电陶炉"
						},
						{
							"list3name":"煮蛋器"
						},
						{
							"list3name":"电烧烤炉"
						}
					]
				},
				{    
        
					"leftname":"生活电器",
					"list3":[
						{
							"list3name":"电风扇"
						},
						{
							"list3name":"冷风扇"
						},
						{
							"list3name":"空气净化器"
						},
						{
							"list3name":"吸尘器"
						},
						{
							"list3name":"除螨仪"
						},
						{
							"list3name":"扫地机器人"
						},
						{
							"list3name":"除湿机"
						},
						{
							"list3name":"干衣机"
						},{
							"list3name":"加湿器"
						},
						{
							"list3name":"蒸汽拖把/拖地机"
						},
						{
							"list3name":"挂烫机/熨斗"
						},
						{
							"list3name":"电话机"
						},
						{
							"list3name":"饮水机"
						},
						{
							"list3name":"净水器"
						},
						{
							"list3name":"取暖电器"
						},
						{
							"list3name":"毛球修剪器"
						},
						{
							"list3name":"生活电器配件"
						}
					]
				},
				{    
        
					"leftname":"个户健康",
					"list3":[
						{
							"list3name":"剃须刀"
						},
						{
							"list3name":"电动牙刷"
						},
						{
							"list3name":"电吹风"
						},
						{
							"list3name":"美容器"
						},
						{
							"list3name":"洁面仪"
						},
						{
							"list3name":"按摩器"
						},
						{
							"list3name":"健康秤"
						},
						{
							"list3name":"卷/直发器"
						},
						{
							"list3name":"剃/脱毛器"
						},
						{
							"list3name":"理发器"
						},
						{
							"list3name":"足浴盆"
						},
						{
							"list3name":"足疗机"
						},
						{
							"list3name":"按摩椅"
						}
					]
				},
				{    
    
					"leftname":"视听影音",
					"list3":[
						{
							"list3name":"家庭影院"
						},
						{
							"list3name":"KTV音响"
						},
						{
							"list3name":"迷你音响"
						},
						{
							"list3name":"DVD"
						},
						{
							"list3name":"功放"
						},
						{
							"list3name":"回音壁"
						},
						{
							"list3name":"麦克风"
						}
					]
				}
			]
		},
		{
			"list1":"图书/文娱/电子书",
			"list2top":[

				{
					"topname":"玩3C"
				},
				{
					"topname":"手机频道"
				},
				{
					"topname":"网上营业厅"
				},
				{
					"topname":"配件选购中心"
				},
				{
					"topname":"智能数码"
				},
				{
					"topname":"影像Club"
				}
			],
			"list2left":[
				{    

					"leftname":"手机通讯",
					"list3":[
						{
							"list3name":"手机"
						},
						{
							"list3name":"游戏手机"
						},
						{
							"list3name":"老人机"
						},
						{
							"list3name":"对讲机"
						},
						{
							"list3name":"以旧换新"
						},
						{
							"list3name":"手机维修"
						}
					]
				},
				{  
      
					"leftname":"运营商",
					"list3":[
						{
							"list3name":"合约机"
						},
						{
							"list3name":"选号码"
						},
						{
							"list3name":"固话宽带"
						},
						{
							"list3name":"办套餐"
						},
						{
							"list3name":"充话费/流量"
						},
						{
							"list3name":"中国电信"
						},
						{
							"list3name":"中国移动"
						},
						{
							"list3name":"中国联通"
						},
						{
							"list3name":"京东通信"
						},
						{
							"list3name":"170选号"
						},
						{
							"list3name":"上网卡"
						}
					]
				},
				{  
      
					"leftname":"手机配件",
					"list3":[
						{
							"list3name":"手机壳"
						},
						{
							"list3name":"贴膜"
						},
						{
							"list3name":"手机存储卡"
						},
						{
							"list3name":"充电器"
						},
						{
							"list3name":"手机耳机"
						},
						{
							"list3name":"创意配件"
						},
						{
							"list3name":"手机饰品"
						},
						{
							"list3name":"手机电池"
						},
						{
							"list3name":"苹果周边"
						},
						{
							"list3name":"移动电源"
						},
						{
							"list3name":"蓝牙耳机"
						},
						{
							"list3name":"手机支架"
						},
						{
							"list3name":"车载配件"
						},
						{
							"list3name":"拍照配件"
						}
					]
				},
				{  
    
					"leftname":"摄影摄像",
					"list3":[
						{
							"list3name":"单电/微单相机"
						},
						{
							"list3name":"单反相机"
						},
						{
							"list3name":"运动相机"
						},
						{
							"list3name":"摄像机"
						},
						{
							"list3name":"镜头"
						},
						{
							"list3name":"户外器材"
						},
						{
							"list3name":"影棚器材"
						},
						{
							"list3name":"冲印服务"
						},
						{
							"list3name":"数码相框"
						}
					]
				},
				{  
    
					"leftname":"数码配件",
					"list3":[
						{
							"list3name":"存储卡"
						},
						{
							"list3name":"三脚架/云台"
						},
						{
							"list3name":"相机包"
						},
						{
							"list3name":"滤镜"
						},
						{
							"list3name":"闪光灯/手柄"
						},
						{
							"list3name":"相机清洁/贴膜"
						},
						{
							"list3name":"机身附件"
						},
						{
							"list3name":"镜头附件"
						},
						{
							"list3name":"读卡器"
						},
						{
							"list3name":"支架"
						},
						{
							"list3name":"电池/充电器"
						}
					]
				},
				{  
      
					"leftname":"影音娱乐",
					"list3":[
						{
							"list3name":"耳机/耳麦"
						},
						{
							"list3name":"音箱/音响"
						},
						{
							"list3name":"智能音箱"
						},
						{
							"list3name":"便携/无线音箱"
						},
						{
							"list3name":"收音机"
						},
						{
							"list3name":"麦克风"
						},
						{
							"list3name":"MP3/MP4"
						},
						{
							"list3name":"专业音频"
						},
						{
							"list3name":"音频线"
						}
					]
				},
				{   
    
					"leftname":"智能设备",
					"list3":[
						{
							"list3name":"智能手环"
						},
						{
							"list3name":"智能手表"
						},
						{
							"list3name":"智能眼镜"
						},
						{
							"list3name":"智能机器人"
						},
						{
							"list3name":"运动跟踪器"
						},
						{
							"list3name":"健康监测"
						},
						{
							"list3name":"智能配饰"
						},
						{
							"list3name":"智能家居"
						},
						{
							"list3name":"体感车"
						},
						{
							"list3name":"无人机"
						}
					]
				},
				{  
              
					"leftname":"电子教育",
					"list3":[
						{
							"list3name":"学生平板"
						},
						{
							"list3name":"点读机/笔"
						},
						{
							"list3name":"早教益智"
						},
						{
							"list3name":"录音笔"
						},
						{
							"list3name":"电纸书"
						},
						{
							"list3name":"电子词典"
						},
						{
							"list3name":"复读机"
						},
						{
							"list3name":"翻译机"
						}
					]
				}
			]	
		},
		{
			"list1":"机票/酒店/旅游/生活",
			"list2top":[

				{
					"topname":"玩3C"
				},
				{
					"topname":"本周热卖"
				},
				{
					"topname":"企业采购"
				},
				{
					"topname":"GAME"
				},
				{
					"topname":"装机大师"
				},
				{
					"topname":"私人定制"
				}
			],
			"list2left":[
				{    
    
					"leftname":"电脑整机",
					"list3":[
						{
							"list3name":"笔记本"
						},
						{
							"list3name":"游戏本"
						},
						{
							"list3name":"平板电脑"
						},
						{
							"list3name":"平板电脑配件"
						},
						{
							"list3name":"台式机"
						},
						{
							"list3name":"一体机"
						},
						{
							"list3name":"服务器/工作站"
						},
						{
							"list3name":"笔记本配件"
						}
					]
				},
				{    
    
					"leftname":"电脑配件",
					"list3":[
						{
							"list3name":"显示器"
						},
						{
							"list3name":"CPU"
						},
						{
							"list3name":"主板"
						},
						{
							"list3name":"显卡"
						},
						{
							"list3name":"硬盘"
						},
						{
							"list3name":"内存"
						},
						{
							"list3name":"机箱"
						},
						{
							"list3name":"电源"
						},
						{
							"list3name":"散热器"
						},
						{
							"list3name":"显示器支架"
						},
						{
							"list3name":"刻录机/光驱"
						},
						{
							"list3name":"声卡/扩展卡"
						},
						{
							"list3name":"装机配件"
						},
						{
							"list3name":"SSD固态硬盘"
						},
						{
							"list3name":"组装电脑"
						},
						{
							"list3name":"USB分线器"
						}
					]
				},
				{    

					"leftname":"外设产品",
					"list3":[
						{
							"list3name":"鼠标"
						},
						{
							"list3name":"键盘"
						},
						{
							"list3name":"键鼠套装"
						},
						{
							"list3name":"网络仪表仪器"
						},
						{
							"list3name":"U盘"
						},
						{
							"list3name":"移动硬盘"
						},
						{
							"list3name":"鼠标垫"
						},
						{
							"list3name":"摄像头"
						},
						{
							"list3name":"线缆"
						},
						{
							"list3name":"手写板"
						},
						{
							"list3name":"硬盘盒"
						},
						{
							"list3name":"电脑工具"
						},
						{
							"list3name":"电脑清洁"
						},
						{
							"list3name":"UPS电源"
						},
						{
							"list3name":"插座"
						}
					]
				},
				{    

					"leftname":"游戏设备",
					"list3":[
						{
							"list3name":"游戏机"
						},
						{
							"list3name":"游戏耳机"
						},
						{
							"list3name":"手柄/方向盘"
						},
						{
							"list3name":"游戏软件"
						},
						{
							"list3name":"游戏周边"
						}
					]
				},
				{    
        
					"leftname":"网络产品",
					"list3":[
						{
							"list3name":"路由器"
						},
						{
							"list3name":"网络机顶盒"
						},
						{
							"list3name":"交换机"
						},
						{
							"list3name":"网络存储"
						},
						{
							"list3name":"网卡"
						},
						{
							"list3name":"4G/3G上网"
						},
						{
							"list3name":"网线"
						},
						{
							"list3name":"网络配件"
						}
					]
				},
				{    
    
					"leftname":"办公设备",
					"list3":[
						{
							"list3name":"投影机"
						},
						{
							"list3name":"投影配件"
						},
						{
							"list3name":"多功能一体机"
						},
						{
							"list3name":"打印机"
						},
						{
							"list3name":"传真设备"
						},
						{
							"list3name":"验钞/点钞机"
						},
						{
							"list3name":"扫描设备"
						},
						{
							"list3name":"复合机"
						},
						{
							"list3name":"碎纸机"
						},
						{
							"list3name":"考勤门禁"
						},
						{
							"list3name":"收银机"
						},
						{
							"list3name":"会议音频视频"
						},
						{
							"list3name":"保险柜"
						},
						{
							"list3name":"装订/封装机"
						},
						{
							"list3name":"安防监控"
						},
						{
							"list3name":"办公家具"
						},
						{
							"list3name":"白板"
						}
					]
				},
				{    
 
					"leftname":"文具",
					"list3":[
						{
							"list3name":"笔类"
						},
						{
							"list3name":"本册/便签"
						},
						{
							"list3name":"办公文具"
						},
						{
							"list3name":"文件收纳"
						},
						{
							"list3name":"学生文具"
						},
						{
							"list3name":"计算器"
						},
						{
							"list3name":"画具画材"
						},
						{
							"list3name":"财会用品"
						}
					]
				},
				{    

					"leftname":"耗材",
					"list3":[
						{
							"list3name":"硒鼓/墨粉"
						},
						{
							"list3name":"墨盒"
						},
						{
							"list3name":"色带"
						},
						{
							"list3name":"纸类"
						},
						{
							"list3name":"刻录光盘"
						}
					]
				},
				{    
    
					"leftname":"服务产品",
					"list3":[
						{
							"list3name":"延保服务"
						},
						{
							"list3name":"上门安装"
						},
						{
							"list3name":"维修保养"
						},
						{
							"list3name":"电脑软件"
						}
					]
				}
			]
		},
		{
			"list1":"理财/众筹/白条/保险",
			"list2top":[
				{
					"topname":"家电馆"
				},
				{
					"topname":"家电专卖店"
				},
				{
					"topname":"家电服务"
				},
				{
					"topname":"企业采购"
				},
				{
					"topname":"商用电器"
				}
			],
			"list2left":[
				{
					"leftname":"电视",
					"list3":[
						{
							"list3name":"超薄电视"
						},
						{
							"list3name":"全面屏电视"
						},
						{
							"list3name":"智能电视"
						},
						{
							"list3name":"OLED电视"
						},
						{
							"list3name":"曲面电视"
						},
						{
							"list3name":"4K超清电视"
						},
						{
							"list3name":"55英寸"
						},
						{
							"list3name":"65英寸"
						},
						{
							"list3name":"电视配件"
						}
					]
				},
				{    
    
					"leftname":"空调",
					"list3":[
						{
							"list3name":"空调挂机"
						},
						{
							"list3name":"空调柜机"
						},
						{
							"list3name":"精选推荐"
						},
						{
							"list3name":"中央空调"
						},
						{
							"list3name":"移动空调"
						},
						{
							"list3name":"省电空调"
						},
						{
							"list3name":"变频空调"
						},
						{
							"list3name":"以旧换新"
						}
					]
				},
				{    

					"leftname":"洗衣机",
					"list3":[
						{
							"list3name":"滚筒洗衣机"
						},
						{
							"list3name":"洗烘一体机"
						},
						{
							"list3name":"波轮洗衣机"
						},
						{
							"list3name":"迷你洗衣机"
						},
						{
							"list3name":"烘干机"
						},
						{
							"list3name":"洗衣机配件"
						}
					]
				},
				{    
        
					"leftname":"冰箱",
					"list3":[
						{
							"list3name":"多门"
						},
						{
							"list3name":"对开门"
						},
						{
							"list3name":"三门"
						},
						{
							"list3name":"双门"
						},
						{
							"list3name":"冷柜/冰吧"
						},
						{
							"list3name":"酒柜"
						},
						{
							"list3name":"冰箱配件"
						}
					]
				},
				{    
        
					"leftname":"厨卫大电",
					"list3":[
						{
							"list3name":"油烟机"
						},
						{
							"list3name":"燃气灶"
						},
						{
							"list3name":"烟灶套装"
						},
						{
							"list3name":"中集成灶"
						},
						{
							"list3name":"消毒柜"
						},
						{
							"list3name":"洗碗机"
						},
						{
							"list3name":"电热水器"
						},
						{
							"list3name":"燃气热水器"
						},
						{
							"list3name":"空气能热水器"
						},
						{
							"list3name":"太阳能热水器"
						},
						{
							"list3name":"嵌入式厨电"
						},
						{
							"list3name":"烟机灶具配件"
						}
					]
				},
				{    
        
					"leftname":"厨房小电",
					"list3":[
						{
							"list3name":"破壁机"
						},
						{
							"list3name":"电烤箱"
						},
						{
							"list3name":"电饭煲"
						},
						{
							"list3name":"电压力锅"
						},
						{
							"list3name":"电炖锅"
						},
						{
							"list3name":"豆浆机"
						},
						{
							"list3name":"料理机"
						},
						{
							"list3name":"咖啡机"
						},
						{
							"list3name":"电饼铛"
						},
						{
							"list3name":"榨汁机/原汁机"
						},
						{
							"list3name":"电水壶/热水瓶"
						},
						{
							"list3name":"微波炉"
						},
						{
							"list3name":"多用途锅"
						},
						{
							"list3name":"养生壶"
						},
						{
							"list3name":"电磁炉"
						},
						{
							"list3name":"面包机"
						},
						{
							"list3name":"空气炸锅"
						},
						{
							"list3name":"面条机"
						},
						{
							"list3name":"电陶炉"
						},
						{
							"list3name":"煮蛋器"
						},
						{
							"list3name":"电烧烤炉"
						}
					]
				},
				{    
        
					"leftname":"生活电器",
					"list3":[
						{
							"list3name":"电风扇"
						},
						{
							"list3name":"冷风扇"
						},
						{
							"list3name":"空气净化器"
						},
						{
							"list3name":"吸尘器"
						},
						{
							"list3name":"除螨仪"
						},
						{
							"list3name":"扫地机器人"
						},
						{
							"list3name":"除湿机"
						},
						{
							"list3name":"干衣机"
						},{
							"list3name":"加湿器"
						},
						{
							"list3name":"蒸汽拖把/拖地机"
						},
						{
							"list3name":"挂烫机/熨斗"
						},
						{
							"list3name":"电话机"
						},
						{
							"list3name":"饮水机"
						},
						{
							"list3name":"净水器"
						},
						{
							"list3name":"取暖电器"
						},
						{
							"list3name":"毛球修剪器"
						},
						{
							"list3name":"生活电器配件"
						}
					]
				},
				{    
        
					"leftname":"个户健康",
					"list3":[
						{
							"list3name":"剃须刀"
						},
						{
							"list3name":"电动牙刷"
						},
						{
							"list3name":"电吹风"
						},
						{
							"list3name":"美容器"
						},
						{
							"list3name":"洁面仪"
						},
						{
							"list3name":"按摩器"
						},
						{
							"list3name":"健康秤"
						},
						{
							"list3name":"卷/直发器"
						},
						{
							"list3name":"剃/脱毛器"
						},
						{
							"list3name":"理发器"
						},
						{
							"list3name":"足浴盆"
						},
						{
							"list3name":"足疗机"
						},
						{
							"list3name":"按摩椅"
						}
					]
				},
				{    
    
					"leftname":"视听影音",
					"list3":[
						{
							"list3name":"家庭影院"
						},
						{
							"list3name":"KTV音响"
						},
						{
							"list3name":"迷你音响"
						},
						{
							"list3name":"DVD"
						},
						{
							"list3name":"功放"
						},
						{
							"list3name":"回音壁"
						},
						{
							"list3name":"麦克风"
						}
					]
				}
			]
		},
		{
			"list1":"安装/维修/清洗/二手",
			"list2top":[

				{
					"topname":"玩3C"
				},
				{
					"topname":"手机频道"
				},
				{
					"topname":"网上营业厅"
				},
				{
					"topname":"配件选购中心"
				},
				{
					"topname":"智能数码"
				},
				{
					"topname":"影像Club"
				}
			],
			"list2left":[
				{    

					"leftname":"手机通讯",
					"list3":[
						{
							"list3name":"手机"
						},
						{
							"list3name":"游戏手机"
						},
						{
							"list3name":"老人机"
						},
						{
							"list3name":"对讲机"
						},
						{
							"list3name":"以旧换新"
						},
						{
							"list3name":"手机维修"
						}
					]
				},
				{  
      
					"leftname":"运营商",
					"list3":[
						{
							"list3name":"合约机"
						},
						{
							"list3name":"选号码"
						},
						{
							"list3name":"固话宽带"
						},
						{
							"list3name":"办套餐"
						},
						{
							"list3name":"充话费/流量"
						},
						{
							"list3name":"中国电信"
						},
						{
							"list3name":"中国移动"
						},
						{
							"list3name":"中国联通"
						},
						{
							"list3name":"京东通信"
						},
						{
							"list3name":"170选号"
						},
						{
							"list3name":"上网卡"
						}
					]
				},
				{  
      
					"leftname":"手机配件",
					"list3":[
						{
							"list3name":"手机壳"
						},
						{
							"list3name":"贴膜"
						},
						{
							"list3name":"手机存储卡"
						},
						{
							"list3name":"充电器"
						},
						{
							"list3name":"手机耳机"
						},
						{
							"list3name":"创意配件"
						},
						{
							"list3name":"手机饰品"
						},
						{
							"list3name":"手机电池"
						},
						{
							"list3name":"苹果周边"
						},
						{
							"list3name":"移动电源"
						},
						{
							"list3name":"蓝牙耳机"
						},
						{
							"list3name":"手机支架"
						},
						{
							"list3name":"车载配件"
						},
						{
							"list3name":"拍照配件"
						}
					]
				},
				{  
    
					"leftname":"摄影摄像",
					"list3":[
						{
							"list3name":"单电/微单相机"
						},
						{
							"list3name":"单反相机"
						},
						{
							"list3name":"运动相机"
						},
						{
							"list3name":"摄像机"
						},
						{
							"list3name":"镜头"
						},
						{
							"list3name":"户外器材"
						},
						{
							"list3name":"影棚器材"
						},
						{
							"list3name":"冲印服务"
						},
						{
							"list3name":"数码相框"
						}
					]
				},
				{  
    
					"leftname":"数码配件",
					"list3":[
						{
							"list3name":"存储卡"
						},
						{
							"list3name":"三脚架/云台"
						},
						{
							"list3name":"相机包"
						},
						{
							"list3name":"滤镜"
						},
						{
							"list3name":"闪光灯/手柄"
						},
						{
							"list3name":"相机清洁/贴膜"
						},
						{
							"list3name":"机身附件"
						},
						{
							"list3name":"镜头附件"
						},
						{
							"list3name":"读卡器"
						},
						{
							"list3name":"支架"
						},
						{
							"list3name":"电池/充电器"
						}
					]
				},
				{  
      
					"leftname":"影音娱乐",
					"list3":[
						{
							"list3name":"耳机/耳麦"
						},
						{
							"list3name":"音箱/音响"
						},
						{
							"list3name":"智能音箱"
						},
						{
							"list3name":"便携/无线音箱"
						},
						{
							"list3name":"收音机"
						},
						{
							"list3name":"麦克风"
						},
						{
							"list3name":"MP3/MP4"
						},
						{
							"list3name":"专业音频"
						},
						{
							"list3name":"音频线"
						}
					]
				},
				{   
    
					"leftname":"智能设备",
					"list3":[
						{
							"list3name":"智能手环"
						},
						{
							"list3name":"智能手表"
						},
						{
							"list3name":"智能眼镜"
						},
						{
							"list3name":"智能机器人"
						},
						{
							"list3name":"运动跟踪器"
						},
						{
							"list3name":"健康监测"
						},
						{
							"list3name":"智能配饰"
						},
						{
							"list3name":"智能家居"
						},
						{
							"list3name":"体感车"
						},
						{
							"list3name":"无人机"
						}
					]
				},
				{  
              
					"leftname":"电子教育",
					"list3":[
						{
							"list3name":"学生平板"
						},
						{
							"list3name":"点读机/笔"
						},
						{
							"list3name":"早教益智"
						},
						{
							"list3name":"录音笔"
						},
						{
							"list3name":"电纸书"
						},
						{
							"list3name":"电子词典"
						},
						{
							"list3name":"复读机"
						},
						{
							"list3name":"翻译机"
						}
					]
				}
			]	
		},
		{
			"list1":"工业品",
			"list2top":[

				{
					"topname":"玩3C"
				},
				{
					"topname":"本周热卖"
				},
				{
					"topname":"企业采购"
				},
				{
					"topname":"GAME"
				},
				{
					"topname":"装机大师"
				},
				{
					"topname":"私人定制"
				}
			],
			"list2left":[
				{    
    
					"leftname":"电脑整机",
					"list3":[
						{
							"list3name":"笔记本"
						},
						{
							"list3name":"游戏本"
						},
						{
							"list3name":"平板电脑"
						},
						{
							"list3name":"平板电脑配件"
						},
						{
							"list3name":"台式机"
						},
						{
							"list3name":"一体机"
						},
						{
							"list3name":"服务器/工作站"
						},
						{
							"list3name":"笔记本配件"
						}
					]
				},
				{    
    
					"leftname":"电脑配件",
					"list3":[
						{
							"list3name":"显示器"
						},
						{
							"list3name":"CPU"
						},
						{
							"list3name":"主板"
						},
						{
							"list3name":"显卡"
						},
						{
							"list3name":"硬盘"
						},
						{
							"list3name":"内存"
						},
						{
							"list3name":"机箱"
						},
						{
							"list3name":"电源"
						},
						{
							"list3name":"散热器"
						},
						{
							"list3name":"显示器支架"
						},
						{
							"list3name":"刻录机/光驱"
						},
						{
							"list3name":"声卡/扩展卡"
						},
						{
							"list3name":"装机配件"
						},
						{
							"list3name":"SSD固态硬盘"
						},
						{
							"list3name":"组装电脑"
						},
						{
							"list3name":"USB分线器"
						}
					]
				},
				{    

					"leftname":"外设产品",
					"list3":[
						{
							"list3name":"鼠标"
						},
						{
							"list3name":"键盘"
						},
						{
							"list3name":"键鼠套装"
						},
						{
							"list3name":"网络仪表仪器"
						},
						{
							"list3name":"U盘"
						},
						{
							"list3name":"移动硬盘"
						},
						{
							"list3name":"鼠标垫"
						},
						{
							"list3name":"摄像头"
						},
						{
							"list3name":"线缆"
						},
						{
							"list3name":"手写板"
						},
						{
							"list3name":"硬盘盒"
						},
						{
							"list3name":"电脑工具"
						},
						{
							"list3name":"电脑清洁"
						},
						{
							"list3name":"UPS电源"
						},
						{
							"list3name":"插座"
						}
					]
				},
				{    

					"leftname":"游戏设备",
					"list3":[
						{
							"list3name":"游戏机"
						},
						{
							"list3name":"游戏耳机"
						},
						{
							"list3name":"手柄/方向盘"
						},
						{
							"list3name":"游戏软件"
						},
						{
							"list3name":"游戏周边"
						}
					]
				},
				{    
        
					"leftname":"网络产品",
					"list3":[
						{
							"list3name":"路由器"
						},
						{
							"list3name":"网络机顶盒"
						},
						{
							"list3name":"交换机"
						},
						{
							"list3name":"网络存储"
						},
						{
							"list3name":"网卡"
						},
						{
							"list3name":"4G/3G上网"
						},
						{
							"list3name":"网线"
						},
						{
							"list3name":"网络配件"
						}
					]
				},
				{    
    
					"leftname":"办公设备",
					"list3":[
						{
							"list3name":"投影机"
						},
						{
							"list3name":"投影配件"
						},
						{
							"list3name":"多功能一体机"
						},
						{
							"list3name":"打印机"
						},
						{
							"list3name":"传真设备"
						},
						{
							"list3name":"验钞/点钞机"
						},
						{
							"list3name":"扫描设备"
						},
						{
							"list3name":"复合机"
						},
						{
							"list3name":"碎纸机"
						},
						{
							"list3name":"考勤门禁"
						},
						{
							"list3name":"收银机"
						},
						{
							"list3name":"会议音频视频"
						},
						{
							"list3name":"保险柜"
						},
						{
							"list3name":"装订/封装机"
						},
						{
							"list3name":"安防监控"
						},
						{
							"list3name":"办公家具"
						},
						{
							"list3name":"白板"
						}
					]
				},
				{    
 
					"leftname":"文具",
					"list3":[
						{
							"list3name":"笔类"
						},
						{
							"list3name":"本册/便签"
						},
						{
							"list3name":"办公文具"
						},
						{
							"list3name":"文件收纳"
						},
						{
							"list3name":"学生文具"
						},
						{
							"list3name":"计算器"
						},
						{
							"list3name":"画具画材"
						},
						{
							"list3name":"财会用品"
						}
					]
				},
				{    

					"leftname":"耗材",
					"list3":[
						{
							"list3name":"硒鼓/墨粉"
						},
						{
							"list3name":"墨盒"
						},
						{
							"list3name":"色带"
						},
						{
							"list3name":"纸类"
						},
						{
							"list3name":"刻录光盘"
						}
					]
				},
				{    
    
					"leftname":"服务产品",
					"list3":[
						{
							"list3name":"延保服务"
						},
						{
							"list3name":"上门安装"
						},
						{
							"list3name":"维修保养"
						},
						{
							"list3name":"电脑软件"
						}
					]
				}
			]
		}		
	]
}